acace_retry_handler/__init__.py
acace_retry_handler-0.1.0.dist-info/METADATA
acace_retry_handler-0.1.0.dist-info/WHEEL
acace_retry_handler-0.1.0.dist-info/RECORD
